{"access_right":"open","communities":[{"identifier":"zenodo"}],"creators":[{"name":"Caribbean Development Bank"},{"name":"CARICOM"},{"name":"Organisation of Eastern Caribbean States"},{"name":"Björn Haßler"},{"name":"Callista Regis"},{"name":"Abdullah Khalayleh"},{"name":"Chris McBurnie"},{"name":"Ghislaine Megha-Bongnkar"},{"name":"Tom Blower"}],"description":"No description available.","doi":"10.5281/zenodo.5306708","license":"CC-BY-4.0","prereserve_doi":{"doi":"10.5281/zenodo.5306708","recid":5306708},"publication_date":"2021-06-23","publication_type":"report","related_identifiers":[{"identifier":"zotero://select/groups/2129771/items/NXIGDXWV","relation":"isAlternateIdentifier","resource_type":"other","scheme":"url"}],"title":"The CDB / CARICOM / OECS Model Learning Recovery and Improvement Programme for Caribbean Schools: Let's REAP! — Overview","upload_type":"publication"}